LICENSE
MANIFEST.in
README.rst
setup.cfg
setup.py
versioneer.py
solstice/__init__.py
solstice/libs/__init__.py
solstice/libs/picker/__init__.py
solstice/libs/picker/__logging__.ini
solstice/libs/picker/__version__.py
solstice/libs/picker/_version.py
solstice/libs/picker/scripts/__init__.py
solstice_libs_picker.egg-info/PKG-INFO
solstice_libs_picker.egg-info/SOURCES.txt
solstice_libs_picker.egg-info/dependency_links.txt
solstice_libs_picker.egg-info/not-zip-safe
solstice_libs_picker.egg-info/requires.txt
solstice_libs_picker.egg-info/top_level.txt
tests/__init__.py
tests/test_general.py