Metadata-Version: 2.1
Name: solstice-libs-picker
Version: 0.0.1
Summary: Library to create data driven based pickers for rigs for Solstice
Home-page: https://github.com/Solstice-Short-Film/solstice-libs-picker
Author: Tomas Poveda
Author-email: tpovedatd@gmail.com
License: MIT
Platform: UNKNOWN
Provides-Extra: test
Provides-Extra: dev
